pysolidarity/__init__.py
pysolidarity/_version.py
pysolidarity/client.py
pysolidarity/errors.py
pysolidarity/factory.py
pysolidarity/http.py
pysolidarity/normalize.py
pysolidarity/py.typed
pysolidarity/retry.py
pysolidarity/types.py
pysolidarity/resources/__init__.py
pysolidarity/resources/users.py
pysolidarity-0.5.1.dist-info/METADATA
pysolidarity-0.5.1.dist-info/WHEEL
pysolidarity-0.5.1.dist-info/RECORD
