Metadata-Version: 2.4
Name: pysolidarity
Version: 0.5.1
Summary: A Solidarity.Tech Python API Wrapper
Project-URL: Homepage, https://www.solidarity.tech
Project-URL: Issues, https://github.com/your-org/pysolidarity/issues
Project-URL: Source, https://github.com/your-org/pysolidarity
Author-email: James Brunet <james@brunet.dev>
License: MIT
Keywords: api,sdk,solidarity
Classifier: License :: OSI Approved :: MIT License
Classifier: Programming Language :: Python :: 3
Classifier: Programming Language :: Python :: 3 :: Only
Classifier: Typing :: Typed
Requires-Python: >=3.9
Requires-Dist: requests<3.0,>=2.31
Provides-Extra: dev
Requires-Dist: mypy>=1.10.0; extra == 'dev'
Requires-Dist: pytest-cov>=4.1; extra == 'dev'
Requires-Dist: pytest>=7.0; extra == 'dev'
Requires-Dist: responses>=0.25.0; extra == 'dev'
Requires-Dist: ruff>=0.5.0; extra == 'dev'
Requires-Dist: types-requests; extra == 'dev'
Provides-Extra: rate
Requires-Dist: redis>=5.0; extra == 'rate'
